openrxn_perovskite_optimizer/__init__.py
openrxn_perovskite_optimizer/__main__.py
openrxn_perovskite_optimizer/cli.py
openrxn_perovskite_optimizer/agents/__init__.py
openrxn_perovskite_optimizer/agents/base.py
openrxn_perovskite_optimizer/agents/characterization.py
openrxn_perovskite_optimizer/agents/discovery.py
openrxn_perovskite_optimizer/agents/experimental.py
openrxn_perovskite_optimizer/agents/optimization.py
openrxn_perovskite_optimizer/agents/synthesis.py
openrxn_perovskite_optimizer/api/__init__.py
openrxn_perovskite_optimizer/api/dependencies.py
openrxn_perovskite_optimizer/api/main.py
openrxn_perovskite_optimizer/api/routes/__init__.py
openrxn_perovskite_optimizer/api/routes/analysis.py
openrxn_perovskite_optimizer/api/routes/experiments.py
openrxn_perovskite_optimizer/api/routes/materials.py
openrxn_perovskite_optimizer/api/routes/optimization.py
openrxn_perovskite_optimizer/api/schemas/__init__.py
openrxn_perovskite_optimizer/api/schemas/experiments.py
openrxn_perovskite_optimizer/api/schemas/materials.py
openrxn_perovskite_optimizer/api/schemas/responses.py
openrxn_perovskite_optimizer/database/__init__.py
openrxn_perovskite_optimizer/database/connection.py
openrxn_perovskite_optimizer/database/crud.py
openrxn_perovskite_optimizer/database/models.py
openrxn_perovskite_optimizer/database/migrations/__init__.py
openrxn_perovskite_optimizer/database/migrations/env.py
openrxn_perovskite_optimizer/experimental/__init__.py
openrxn_perovskite_optimizer/experimental/characterization.py
openrxn_perovskite_optimizer/experimental/device_fabrication.py
openrxn_perovskite_optimizer/experimental/synthesis_protocols.py
openrxn_perovskite_optimizer/experimental/testing.py
openrxn_perovskite_optimizer/ml/__init__.py
openrxn_perovskite_optimizer/ml/active_learning.py
openrxn_perovskite_optimizer/ml/graph_networks.py
openrxn_perovskite_optimizer/ml/optimization.py
openrxn_perovskite_optimizer/ml/property_prediction.py
openrxn_perovskite_optimizer/ml/uncertainty.py
openrxn_perovskite_optimizer-1.0.0.dist-info/METADATA
openrxn_perovskite_optimizer-1.0.0.dist-info/WHEEL
openrxn_perovskite_optimizer-1.0.0.dist-info/entry_points.txt
openrxn_perovskite_optimizer-1.0.0.dist-info/licenses/LICENSE
openrxn_perovskite_optimizer-1.0.0.dist-info/RECORD
